aegis_vision/__init__.py
aegis_vision/_opencv_fix.py
aegis_vision/agent.py
aegis_vision/agent_auth.py
aegis_vision/agent_cli.py
aegis_vision/ascii_visualizer.py
aegis_vision/converters.py
aegis_vision/dataset_utils.py
aegis_vision/environment_check.py
aegis_vision/export_coreml_standalone.py
aegis_vision/gpu_detection_linux.py
aegis_vision/gpu_detection_macos.py
aegis_vision/gpu_detection_pytorch.py
aegis_vision/gpu_detection_rocm.py
aegis_vision/headless_utils.py
aegis_vision/kaggle_uploader.py
aegis_vision/trainer.py
aegis_vision/training_script.py
aegis_vision/utils.py
aegis_vision/export_converters/__init__.py
aegis_vision/export_converters/openvino_converter.py
aegis_vision/export_converters/torchscript_converter.py
aegis_vision-0.2.55.dist-info/licenses/LICENSE
aegis_vision-0.2.55.dist-info/METADATA
aegis_vision-0.2.55.dist-info/WHEEL
aegis_vision-0.2.55.dist-info/entry_points.txt
aegis_vision-0.2.55.dist-info/top_level.txt
aegis_vision-0.2.55.dist-info/RECORD
