Metadata-Version: 2.4
Name: aegis-vision
Version: 0.2.55
Summary: Cloud-native computer vision model training toolkit for Aegis AI
Author-email: Aegis AI Team <your-email@example.com>
License: MIT
Project-URL: Homepage, https://github.com/your-org/aegis-vision
Project-URL: Documentation, https://aegis-vision.readthedocs.io
Project-URL: Repository, https://github.com/your-org/aegis-vision
Project-URL: Bug Tracker, https://github.com/your-org/aegis-vision/issues
Keywords: computer-vision,yolo,model-training,kaggle,wandb,object-detection
Classifier: Development Status :: 3 - Alpha
Classifier: Intended Audience :: Developers
Classifier: Intended Audience :: Science/Research
Classifier: License :: OSI Approved :: MIT License
Classifier: Programming Language :: Python :: 3
Classifier: Programming Language :: Python :: 3.9
Classifier: Programming Language :: Python :: 3.10
Classifier: Programming Language :: Python :: 3.11
Classifier: Topic :: Scientific/Engineering :: Artificial Intelligence
Classifier: Topic :: Scientific/Engineering :: Image Recognition
Requires-Python: >=3.9
License-File: LICENSE
Requires-Dist: pillow>=10.0.0
Requires-Dist: numpy<2.0.0,>=1.24.0
Requires-Dist: wandb>=0.15.0
Requires-Dist: pyyaml>=6.0
Requires-Dist: tqdm>=4.65.0
Requires-Dist: psutil>=5.9.0
Requires-Dist: firebase-admin>=6.0.0
Requires-Dist: google-cloud-firestore>=2.11.0
Requires-Dist: requests>=2.31.0
Requires-Dist: kaggle>=1.5.0
Requires-Dist: kagglehub>=0.2.0
Requires-Dist: datasets>=2.16.0
Requires-Dist: huggingface-hub>=0.20.0
Requires-Dist: coremltools>=8.0.0; platform_machine != "aarch64" or sys_platform == "darwin"
Provides-Extra: training
Requires-Dist: ultralytics>=8.0.0; extra == "training"
Requires-Dist: pycocotools>=2.0.6; extra == "training"
Provides-Extra: dev
Requires-Dist: pytest>=7.4.0; extra == "dev"
Requires-Dist: black>=23.0.0; extra == "dev"
Requires-Dist: ruff>=0.1.0; extra == "dev"
Requires-Dist: mypy>=1.5.0; extra == "dev"
Provides-Extra: all
Requires-Dist: aegis-vision[dev,training]; extra == "all"
Dynamic: license-file
